gyver/__init__.py
gyver/attrs/__init__.py
gyver/attrs/camel.py
gyver/attrs/converters/__init__.py
gyver/attrs/converters/json.py
gyver/attrs/converters/utils.py
gyver/attrs/field.py
gyver/attrs/helpers.py
gyver/attrs/main.py
gyver/attrs/methods.py
gyver/attrs/py.typed
gyver/attrs/resolver.py
gyver/attrs/schema.py
gyver/attrs/shortcuts.py
gyver/attrs/utils/__init__.py
gyver/attrs/utils/factory.py
gyver/attrs/utils/functions.py
gyver/attrs/utils/typedef.py
gyver_attrs-0.9.4.dist-info/LICENSE
gyver_attrs-0.9.4.dist-info/METADATA
gyver_attrs-0.9.4.dist-info/WHEEL
gyver_attrs-0.9.4.dist-info/RECORD
