Metadata-Version: 2.1
Name: gyver-attrs
Version: 0.9.4
Summary: 
Author: Gustavo Cardoso
Author-email: self.gustavocorrea@gmail.com
Requires-Python: >=3.9,<4.0
Classifier: Programming Language :: Python :: 3
Classifier: Programming Language :: Python :: 3.9
Classifier: Programming Language :: Python :: 3.10
Classifier: Programming Language :: Python :: 3.11
Classifier: Programming Language :: Python :: 3.12
Requires-Dist: gyver-attrs-converter (>=0.4.2,<0.5.0)
Requires-Dist: lazy-fields (>=1.0.1,<2.0.0)
Requires-Dist: orjson (>=3.10.0,<4.0.0)
Requires-Dist: typing-extensions (>=4.7.1,<5.0.0)
